{
    "geometry_resources": [
        {
            "id": "Rock_000",
            "mesh": {
                "index_arrays": [
                    {
                        "material": 0,
                        "size": 3,
                        "values": [
                            0,
                            1,
                            2,
                            3,
                            4,
                            5,
                            6,
                            7,
                            8,
                            9,
                            10,
                            11,
                            12,
                            13,
                            14,
                            15,
                            16,
                            17,
                            18,
                            19,
                            20,
                            21,
                            22,
                            23,
                            24,
                            25,
                            26,
                            27,
                            28,
                            29,
                            30,
                            31,
                            32,
                            33,
                            34,
                            35,
                            36,
                            37,
                            38,
                            39,
                            40,
                            41,
                            42,
                            43,
                            44,
                            45,
                            46,
                            47,
                            48,
                            49,
                            50,
                            51,
                            52,
                            53,
                            54,
                            55,
                            56,
                            57,
                            58,
                            59
                        ]
                    }
                ],
                "primitive": "triangles",
                "vertex_arrays": [
                    {
                        "attrib": "position",
                        "size": 3,
                        "values": [
                            1.6163005057023838e-05,
                            0.0,
                            -0.46918949484825134,
                            0.5491441488265991,
                            -0.4120197296142578,
                            -0.2285299301147461,
                            -0.19124427437782288,
                            -0.6121712923049927,
                            -0.19461864233016968,
                            0.5491441488265991,
                            -0.4120197296142578,
                            -0.2285299301147461,
                            1.6163005057023838e-05,
                            0.0,
                            -0.46918949484825134,
                            0.43329110741615295,
                            0.33101680874824524,
                            -0.15363483130931854,
                            1.6163005057023838e-05,
                            0.0,
                            -0.46918949484825134,
                            -0.19124427437782288,
                            -0.6121712923049927,
                            -0.19461864233016968,
                            -0.6450415253639221,
                            0.0,
                            -0.2126215696334839,
                            1.6163005057023838e-05,
                            0.0,
                            -0.46918949484825134,
                            -0.6450415253639221,
                            0.0,
                            -0.2126215696334839,
                            -0.19699716567993164,
                            0.6292397975921631,
                            -0.20411710441112518,
                            1.6163005057023838e-05,
                            0.0,
                            -0.46918949484825134,
                            -0.19699716567993164,
                            0.6292397975921631,
                            -0.20411710441112518,
                            0.43329110741615295,
                            0.33101680874824524,
                            -0.15363483130931854,
                            0.5491441488265991,
                            -0.4120197296142578,
                            -0.2285299301147461,
                            0.43329110741615295,
                            0.33101680874824524,
                            -0.15363483130931854,
                            0.5249555706977844,
                            0.0,
                            0.14890266954898834,
                            -0.19124427437782288,
                            -0.6121712923049927,
                            -0.19461864233016968,
                            0.5491441488265991,
                            -0.4120197296142578,
                            -0.2285299301147461,
                            0.19629165530204773,
                            -0.6271465420722961,
                            0.20295223593711853,
                            -0.6450415253639221,
                            0.0,
                            -0.2126215696334839,
                            -0.19124427437782288,
                            -0.6121712923049927,
                            -0.19461864233016968,
                            -0.4140300154685974,
                            -0.3175497055053711,
                            0.14118318259716034,
                            -0.19699716567993164,
                            0.6292397975921631,
                            -0.20411710441112518,
                            -0.6450415253639221,
                            0.0,
                            -0.2126215696334839,
                            -0.3753094971179962,
                            0.29047688841819763,
                            0.11615170538425446,
                            0.43329110741615295,
                            0.33101680874824524,
                            -0.15363483130931854,
                            -0.19699716567993164,
                            0.6292397975921631,
                            -0.20411710441112518,
                            0.19104288518428802,
                            0.6115737557411194,
                            0.19428615272045135,
                            0.5491441488265991,
                            -0.4120197296142578,
                            -0.2285299301147461,
                            0.5249555706977844,
                            0.0,
                            0.14890266954898834,
                            0.19629165530204773,
                            -0.6271465420722961,
                            0.20295223593711853,
                            -0.19124427437782288,
                            -0.6121712923049927,
                            -0.19461864233016968,
                            0.19629165530204773,
                            -0.6271465420722961,
                            0.20295223593711853,
                            -0.4140300154685974,
                            -0.3175497055053711,
                            0.14118318259716034,
                            -0.6450415253639221,
                            0.0,
                            -0.2126215696334839,
                            -0.4140300154685974,
                            -0.3175497055053711,
                            0.14118318259716034,
                            -0.3753094971179962,
                            0.29047688841819763,
                            0.11615170538425446,
                            -0.19699716567993164,
                            0.6292397975921631,
                            -0.20411710441112518,
                            -0.3753094971179962,
                            0.29047688841819763,
                            0.11615170538425446,
                            0.19104288518428802,
                            0.6115737557411194,
                            0.19428615272045135,
                            0.43329110741615295,
                            0.33101680874824524,
                            -0.15363483130931854,
                            0.19104288518428802,
                            0.6115737557411194,
                            0.19428615272045135,
                            0.5249555706977844,
                            0.0,
                            0.14890266954898834,
                            0.19629165530204773,
                            -0.6271465420722961,
                            0.20295223593711853,
                            0.5249555706977844,
                            0.0,
                            0.14890266954898834,
                            5.974196938041132e-06,
                            0.0,
                            0.1065046489238739,
                            -0.4140300154685974,
                            -0.3175497055053711,
                            0.14118318259716034,
                            0.19629165530204773,
                            -0.6271465420722961,
                            0.20295223593711853,
                            5.974196938041132e-06,
                            0.0,
                            0.1065046489238739,
                            -0.3753094971179962,
                            0.29047688841819763,
                            0.11615170538425446,
                            -0.4140300154685974,
                            -0.3175497055053711,
                            0.14118318259716034,
                            5.974196938041132e-06,
                            0.0,
                            0.1065046489238739,
                            0.19104288518428802,
                            0.6115737557411194,
                            0.19428615272045135,
                            -0.3753094971179962,
                            0.29047688841819763,
                            0.11615170538425446,
                            5.974196938041132e-06,
                            0.0,
                            0.1065046489238739,
                            0.5249555706977844,
                            0.0,
                            0.14890266954898834,
                            0.19104288518428802,
                            0.6115737557411194,
                            0.19428615272045135,
                            5.974196938041132e-06,
                            0.0,
                            0.1065046489238739
                        ]
                    },
                    {
                        "attrib": "normal",
                        "size": 3,
                        "values": [
                            0.07425282150506973,
                            -0.42733290791511536,
                            -0.9010400176048279,
                            0.07425282150506973,
                            -0.42733290791511536,
                            -0.9010400176048279,
                            0.07425282150506973,
                            -0.42733290791511536,
                            -0.9010400176048279,
                            0.4962380826473236,
                            0.16332003474235535,
                            -0.8526865839958191,
                            0.4962380826473236,
                            0.16332003474235535,
                            -0.8526865839958191,
                            0.4962380826473236,
                            0.16332003474235535,
                            -0.8526865839958191,
                            -0.3538699746131897,
                            -0.288485050201416,
                            -0.8896924257278442,
                            -0.3538699746131897,
                            -0.288485050201416,
                            -0.8896924257278442,
                            -0.3538699746131897,
                            -0.288485050201416,
                            -0.8896924257278442,
                            -0.3562885820865631,
                            0.26579874753952026,
                            -0.89577317237854,
                            -0.3562885820865631,
                            0.26579874753952026,
                            -0.89577317237854,
                            -0.3562885820865631,
                            0.26579874753952026,
                            -0.89577317237854,
                            0.27900275588035583,
                            0.44567903876304626,
                            -0.850604236125946,
                            0.27900275588035583,
                            0.44567903876304626,
                            -0.850604236125946,
                            0.27900275588035583,
                            0.44567903876304626,
                            -0.850604236125946,
                            0.9794414043426514,
                            0.1644846647977829,
                            -0.11678808182477951,
                            0.9794414043426514,
                            0.1644846647977829,
                            -0.11678808182477951,
                            0.9794414043426514,
                            0.1644846647977829,
                            -0.11678808182477951,
                            0.2398531585931778,
                            -0.9328152537345886,
                            -0.26893532276153564,
                            0.2398531585931778,
                            -0.9328152537345886,
                            -0.26893532276153564,
                            0.2398531585931778,
                            -0.9328152537345886,
                            -0.26893532276153564,
                            -0.8031597137451172,
                            -0.5956760048866272,
                            -0.010224886238574982,
                            -0.8031597137451172,
                            -0.5956760048866272,
                            -0.010224886238574982,
                            -0.8031597137451172,
                            -0.5956760048866272,
                            -0.010224886238574982,
                            -0.8056201934814453,
                            0.5715261101722717,
                            0.15599341690540314,
                            -0.8056201934814453,
                            0.5715261101722717,
                            0.15599341690540314,
                            -0.8056201934814453,
                            0.5715261101722717,
                            0.15599341690540314,
                            0.42102521657943726,
                            0.8266169428825378,
                            -0.3734196424484253,
                            0.42102521657943726,
                            0.8266169428825378,
                            -0.3734196424484253,
                            0.42102521657943726,
                            0.8266169428825378,
                            -0.3734196424484253,
                            0.7999402284622192,
                            -0.3791312575340271,
                            0.4651399552822113,
                            0.7999402284622192,
                            -0.3791312575340271,
                            0.4651399552822113,
                            0.7999402284622192,
                            -0.3791312575340271,
                            0.4651399552822113,
                            -0.4459453821182251,
                            -0.7983845472335815,
                            0.4046168029308319,
                            -0.4459453821182251,
                            -0.7983845472335815,
                            0.4046168029308319,
                            -0.4459453821182251,
                            -0.7983845472335815,
                            0.4046168029308319,
                            -0.8025704026222229,
                            0.07547148317098618,
                            0.5917640924453735,
                            -0.8025704026222229,
                            0.07547148317098618,
                            0.5917640924453735,
                            -0.8025704026222229,
                            0.07547148317098618,
                            0.5917640924453735,
                            -0.4786264896392822,
                            0.7229655981063843,
                            0.4982343316078186,
                            -0.4786264896392822,
                            0.7229655981063843,
                            0.4982343316078186,
                            -0.4786264896392822,
                            0.7229655981063843,
                            0.4982343316078186,
                            0.8604746460914612,
                            0.45242297649383545,
                            0.234300434589386,
                            0.8604746460914612,
                            0.45242297649383545,
                            0.234300434589386,
                            0.8604746460914612,
                            0.45242297649383545,
                            0.234300434589386,
                            -0.07985132187604904,
                            0.12705448269844055,
                            0.9886763691902161,
                            -0.07985132187604904,
                            0.12705448269844055,
                            0.9886763691902161,
                            -0.07985132187604904,
                            0.12705448269844055,
                            0.9886763691902161,
                            -0.027277182787656784,
                            0.1435989886522293,
                            0.9892599582672119,
                            -0.027277182787656784,
                            0.1435989886522293,
                            0.9892599582672119,
                            -0.027277182787656784,
                            0.1435989886522293,
                            0.9892599582672119,
                            0.05474119260907173,
                            0.03759147226810455,
                            0.997792661190033,
                            0.05474119260907173,
                            0.03759147226810455,
                            0.997792661190033,
                            0.05474119260907173,
                            0.03759147226810455,
                            0.997792661190033,
                            -0.0680960863828659,
                            -0.12087459862232208,
                            0.9903293251991272,
                            -0.0680960863828659,
                            -0.12087459862232208,
                            0.9903293251991272,
                            -0.0680960863828659,
                            -0.12087459862232208,
                            0.9903293251991272,
                            -0.07994980365037918,
                            -0.11710961908102036,
                            0.9898957014083862,
                            -0.07994980365037918,
                            -0.11710961908102036,
                            0.9898957014083862,
                            -0.07994980365037918,
                            -0.11710961908102036,
                            0.9898957014083862
                        ]
                    }
                ]
            }
        }
    ]
}